{
  "metadata": {
    "scraped_from": "https://haz-map.com/Jobs/300",
    "entity_name": "Roustabouts, Oil & Gas",
    "category": "jobs",
    "uuid": "3ccc493b-c7e1-4b93-ad32-a0401389be6b",
    "scraped_at": "2025-07-23T18:29:56.839003"
  },
  "parsed_at": "2025-07-24T01:20:53.220964",
  "title": "Roustabouts, Oil & Gas",
  "sections": {
    "general": {
      "job_name": {
        "original_name": "Job Name",
        "value": "Roustabouts, Oil & Gas",
        "links": [],
        "cross_references": [
          {
            "type": "name_match",
            "text": "roustabouts, oil & gas",
            "confidence": 1.0,
            "uuid": "3ccc493b-c7e1-4b93-ad32-a0401389be6b",
            "name": "Roustabouts, Oil & Gas",
            "url": "https://haz-map.com/Jobs/300",
            "category": "jobs"
          }
        ]
      },
      "description": {
        "original_name": "Description",
        "value": "Assemble or repair oil field equipment using hand and power tools. Perform other tasks as needed.",
        "links": [],
        "cross_references": []
      },
      "category": {
        "original_name": "Category",
        "value": "Extractive",
        "links": [],
        "cross_references": []
      },
      "soc_code": {
        "original_name": "SOC Code",
        "value": "47-5071",
        "links": [],
        "cross_references": []
      }
    },
    "job_tasks_linked_to_this_job": {
      "job_tasks": {
        "original_name": "Job Tasks",
        "value": "High risk job tasks associated with this job: Work in grease, oil, or tar soaked clothing",
        "links": [
          {
            "text": "Work in grease, oil, or tar soaked clothing",
            "url": "https://haz-map.com/JobTasks/225"
          }
        ],
        "cross_references": [
          {
            "type": "url_match",
            "text": "Work in grease, oil, or tar soaked clothing",
            "url": "https://haz-map.com/JobTasks/225",
            "confidence": 1.0,
            "uuid": "8fa6589b-bcfa-4ffd-ae86-8c81a8e9d7d2",
            "name": "Work in grease, oil, or tar soaked clothing",
            "category": "job_tasks"
          },
          {
            "type": "name_match",
            "text": "oak",
            "confidence": 1.0,
            "uuid": "631b107a-216e-4168-b323-dbb24976e011",
            "name": "Oak",
            "url": "https://haz-map.com/Agents/955",
            "category": "agents"
          },
          {
            "type": "name_match",
            "text": "grease",
            "confidence": 1.0,
            "uuid": "bf476c67-9302-4215-a263-a67d337ab9ef",
            "name": "Grease",
            "url": "https://haz-map.com/Agents/21033",
            "category": "agents"
          }
        ]
      }
    }
  },
  "cross_references": [
    {
      "type": "url_match",
      "text": "Work in grease, oil, or tar soaked clothing",
      "url": "https://haz-map.com/JobTasks/225",
      "confidence": 1.0,
      "uuid": "8fa6589b-bcfa-4ffd-ae86-8c81a8e9d7d2",
      "name": "Work in grease, oil, or tar soaked clothing",
      "category": "job_tasks"
    },
    {
      "type": "name_match",
      "text": "roustabouts, oil & gas",
      "confidence": 1.0,
      "uuid": "3ccc493b-c7e1-4b93-ad32-a0401389be6b",
      "name": "Roustabouts, Oil & Gas",
      "url": "https://haz-map.com/Jobs/300",
      "category": "jobs"
    },
    {
      "type": "name_match",
      "text": "oak",
      "confidence": 1.0,
      "uuid": "631b107a-216e-4168-b323-dbb24976e011",
      "name": "Oak",
      "url": "https://haz-map.com/Agents/955",
      "category": "agents"
    },
    {
      "type": "name_match",
      "text": "grease",
      "confidence": 1.0,
      "uuid": "bf476c67-9302-4215-a263-a67d337ab9ef",
      "name": "Grease",
      "url": "https://haz-map.com/Agents/21033",
      "category": "agents"
    }
  ],
  "all_links": [
    {
      "text": "Work in grease, oil, or tar soaked clothing",
      "url": "https://haz-map.com/JobTasks/225"
    }
  ]
}