{
  "metadata": {
    "scraped_from": "https://haz-map.com/JobTasks/219",
    "entity_name": "Manually \"lay-up\" reinforced polyester resins using styrene",
    "category": "job_tasks",
    "uuid": "31d11ced-5a0e-4e76-98aa-eaf78dbec49a",
    "scraped_at": "2025-07-23T18:15:22.955355"
  },
  "parsed_at": "2025-07-24T01:19:39.708174",
  "title": "Manually \"lay-up\" reinforced polyester resins using styrene",
  "sections": {
    "general": {
      "job_task_name": {
        "original_name": "Job Task Name",
        "value": "Manually \"lay-up\" reinforced polyester resins using styrene",
        "links": [],
        "cross_references": [
          {
            "type": "name_match",
            "text": "manually \"lay-up\" reinforced polyester resins using styrene",
            "confidence": 1.0,
            "uuid": "31d11ced-5a0e-4e76-98aa-eaf78dbec49a",
            "name": "Manually \"lay-up\" reinforced polyester resins using styrene",
            "url": "https://haz-map.com/JobTasks/219",
            "category": "job_tasks"
          },
          {
            "type": "name_match",
            "text": "styrene",
            "confidence": 1.0,
            "uuid": "03c5632f-5079-4688-82bd-0dacf3d0d36a",
            "name": "Styrene",
            "url": "https://haz-map.com/Agents/32",
            "category": "agents"
          }
        ]
      },
      "comments": {
        "original_name": "Comments",
        "value": "Solvents, acute toxic effect; Occupational asthma was reported in 2 workers exposed to styrene. [Malo]",
        "links": [],
        "cross_references": [
          {
            "type": "name_match",
            "text": "solvents, acute toxic effect",
            "confidence": 1.0,
            "uuid": "581e90e3-9d0c-45f0-aa6c-3468c28da129",
            "name": "Solvents, acute toxic effect",
            "url": "https://haz-map.com/Diseases/326",
            "category": "diseases"
          },
          {
            "type": "name_match",
            "text": "styrene",
            "confidence": 1.0,
            "uuid": "03c5632f-5079-4688-82bd-0dacf3d0d36a",
            "name": "Styrene",
            "url": "https://haz-map.com/Agents/32",
            "category": "agents"
          }
        ]
      },
      "job_task_category": {
        "original_name": "Job Task Category",
        "value": "Manufacturing",
        "links": [],
        "cross_references": []
      },
      "reference_link": {
        "original_name": "Reference Link",
        "value": "Occupational asthma due to styrene: two case reports.",
        "links": [
          {
            "text": "Occupational asthma due to styrene: two case reports.",
            "url": "http://www.ncbi.nlm.nih.gov/pubmed/3430203"
          }
        ],
        "cross_references": [
          {
            "type": "name_match",
            "text": "styrene",
            "confidence": 1.0,
            "uuid": "03c5632f-5079-4688-82bd-0dacf3d0d36a",
            "name": "Styrene",
            "url": "https://haz-map.com/Agents/32",
            "category": "agents"
          }
        ]
      },
      "exposed_to": {
        "original_name": "Exposed To",
        "value": "Solvents",
        "links": [],
        "cross_references": []
      }
    },
    "diseases_jobs_and_industries_linked_to_this_job_task": {
      "diseases": {
        "original_name": "Diseases",
        "value": "Diseases associated with this job task: Asthma, occupational Solvents, acute toxic effect",
        "links": [
          {
            "text": "Asthma, occupational",
            "url": "https://haz-map.com/Diseases/23"
          },
          {
            "text": "Solvents, acute toxic effect",
            "url": "https://haz-map.com/Diseases/326"
          }
        ],
        "cross_references": [
          {
            "type": "url_match",
            "text": "Asthma, occupational",
            "url": "https://haz-map.com/Diseases/23",
            "confidence": 1.0,
            "uuid": "29c464cb-36b2-43d8-b6fc-e19a0ea695cb",
            "name": "Asthma, occupational",
            "category": "diseases"
          },
          {
            "type": "url_match",
            "text": "Solvents, acute toxic effect",
            "url": "https://haz-map.com/Diseases/326",
            "confidence": 1.0,
            "uuid": "581e90e3-9d0c-45f0-aa6c-3468c28da129",
            "name": "Solvents, acute toxic effect",
            "category": "diseases"
          }
        ]
      },
      "jobs": {
        "original_name": "Jobs",
        "value": "Jobs associated with this job task: Fiberglass Laminators & Fabricators",
        "links": [
          {
            "text": "Fiberglass Laminators & Fabricators",
            "url": "https://haz-map.com/Jobs/344"
          }
        ],
        "cross_references": [
          {
            "type": "url_match",
            "text": "Fiberglass Laminators & Fabricators",
            "url": "https://haz-map.com/Jobs/344",
            "confidence": 1.0,
            "uuid": "d0a4fa20-372e-45fc-82d1-f61b08362135",
            "name": "Fiberglass Laminators & Fabricators",
            "category": "jobs"
          }
        ]
      },
      "industries": {
        "original_name": "Industries",
        "value": "Industries associated with this job task: Boat Building",
        "links": [
          {
            "text": "Boat Building",
            "url": "https://haz-map.com/Industries/252"
          }
        ],
        "cross_references": [
          {
            "type": "url_match",
            "text": "Boat Building",
            "url": "https://haz-map.com/Industries/252",
            "confidence": 1.0,
            "uuid": "f6604218-b0cf-49b7-b403-cd2cf7901415",
            "name": "Boat Building",
            "category": "industries"
          }
        ]
      }
    }
  },
  "cross_references": [
    {
      "type": "url_match",
      "text": "Asthma, occupational",
      "url": "https://haz-map.com/Diseases/23",
      "confidence": 1.0,
      "uuid": "29c464cb-36b2-43d8-b6fc-e19a0ea695cb",
      "name": "Asthma, occupational",
      "category": "diseases"
    },
    {
      "type": "url_match",
      "text": "Solvents, acute toxic effect",
      "url": "https://haz-map.com/Diseases/326",
      "confidence": 1.0,
      "uuid": "581e90e3-9d0c-45f0-aa6c-3468c28da129",
      "name": "Solvents, acute toxic effect",
      "category": "diseases"
    },
    {
      "type": "url_match",
      "text": "Fiberglass Laminators & Fabricators",
      "url": "https://haz-map.com/Jobs/344",
      "confidence": 1.0,
      "uuid": "d0a4fa20-372e-45fc-82d1-f61b08362135",
      "name": "Fiberglass Laminators & Fabricators",
      "category": "jobs"
    },
    {
      "type": "url_match",
      "text": "Boat Building",
      "url": "https://haz-map.com/Industries/252",
      "confidence": 1.0,
      "uuid": "f6604218-b0cf-49b7-b403-cd2cf7901415",
      "name": "Boat Building",
      "category": "industries"
    },
    {
      "type": "name_match",
      "text": "manually \"lay-up\" reinforced polyester resins using styrene",
      "confidence": 1.0,
      "uuid": "31d11ced-5a0e-4e76-98aa-eaf78dbec49a",
      "name": "Manually \"lay-up\" reinforced polyester resins using styrene",
      "url": "https://haz-map.com/JobTasks/219",
      "category": "job_tasks"
    },
    {
      "type": "name_match",
      "text": "styrene",
      "confidence": 1.0,
      "uuid": "03c5632f-5079-4688-82bd-0dacf3d0d36a",
      "name": "Styrene",
      "url": "https://haz-map.com/Agents/32",
      "category": "agents"
    }
  ],
  "all_links": [
    {
      "text": "Occupational asthma due to styrene: two case reports.",
      "url": "http://www.ncbi.nlm.nih.gov/pubmed/3430203"
    },
    {
      "text": "Asthma, occupational",
      "url": "https://haz-map.com/Diseases/23"
    },
    {
      "text": "Solvents, acute toxic effect",
      "url": "https://haz-map.com/Diseases/326"
    },
    {
      "text": "Fiberglass Laminators & Fabricators",
      "url": "https://haz-map.com/Jobs/344"
    },
    {
      "text": "Boat Building",
      "url": "https://haz-map.com/Industries/252"
    }
  ]
}